[
    {
        "name": "jdk8u162-b12_openj9-0.8.0",
        "binaries": [
            {
                "name": "OpenJDK8-OPENJ9_ppc64le_Linux_jdk8u162-b12_openj9-0.8.0.tar.gz",
                "os": "linux"
            },
            {
                "name": "OpenJDK8-OPENJ9_ppc64_AIX_jdk8u162-b12_openj9-0.8.0.tar.gz",
                "os": "aix"
            },
            {
                "name": "OpenJDK8-OPENJ9_s390x_Linux_jdk8u162-b12_openj9-0.8.0.tar.gz",
                "os": "linux"
            },
            {
                "name": "OpenJDK8-OPENJ9_x64_Linux_jdk8u162-b12_openj9-0.8.0.tar.gz",
                "os": "linux"
            }
        ]
    },
    {
        "name": "jdk8u172-b11",
        "binaries": [
            {
                "name": "OpenJDK8_aarch64_Linux_jdk8u172-b11.tar.gz",
                "os": "linux"
            },
            {
                "name": "OpenJDK8_ppc64le_Linux_jdk8u172-b11.tar.gz",
                "os": "linux"
            },
            {
                "name": "OpenJDK8_ppc64_AIX_jdk8u172-b11.tar.gz",
                "os": "aix"
            },
            {
                "name": "OpenJDK8_s390x_Linux_jdk8u172-b11.tar.gz",
                "os": "linux"
            },
            {
                "name": "OpenJDK8_x64_Linux_jdk8u172-b11.tar.gz",
                "os": "linux"
            },
            {
                "name": "OpenJDK8_x64_Mac_jdk8u172-b11.tar.gz",
                "os": "mac"
            },
            {
                "name": "OpenJDK8_x64_Win_jdk8u172-b11.zip",
                "os": "windows"
            }
        ]
    },
    {
        "name": "jdk8u181-b13",
        "binaries": [
            {
                "name": "OpenJDK8U-jdk_x86-32_windows_hotspot_8u181b13.zip",
                "os": "windows"
            },
            {
                "name": "OpenJDK8U-jre_x86-32_windows_hotspot_8u181b13.zip",
                "os": "windows"
            },
            {
                "name": "OpenJDK8U-jdk_x64_windows_hotspot_8u181b13.zip",
                "os": "windows"
            },
            {
                "name": "OpenJDK8U-jre_x64_windows_hotspot_8u181b13.zip",
                "os": "windows"
            },
            {
                "name": "OpenJDK8U-jdk_ppc64_aix_hotspot_8u181b13.tar.gz",
                "os": "aix"
            },
            {
                "name": "OpenJDK8U-jdk_s390x_linux_hotspot_8u181b13.tar.gz",
                "os": "linux"
            },
            {
                "name": "OpenJDK8U-jdk_x64_linux_hotspot_8u181b13.tar.gz",
                "os": "linux"
            },
            {
                "name": "OpenJDK8U-jdk_x64_mac_hotspot_8u181b13.tar.gz",
                "os": "mac"
            },
            {
                "name": "OpenJDK8U-jre_ppc64_aix_hotspot_8u181b13.tar.gz",
                "os": "aix"
            },
            {
                "name": "OpenJDK8U-jre_s390x_linux_hotspot_8u181b13.tar.gz",
                "os": "linux"
            },
            {
                "name": "OpenJDK8U-jre_x64_linux_hotspot_8u181b13.tar.gz",
                "os": "linux"
            },
            {
                "name": "OpenJDK8U-jre_x64_mac_hotspot_8u181b13.tar.gz",
                "os": "mac"
            }
        ]
    },
    {
        "name": "jdk8u181-b13_openj9-0.9.0",
        "binaries": [
            {
                "name": "OpenJDK8-OPENJ9_ppc64le_Linux_jdk8u181-b13_openj9-0.9.0.tar.gz",
                "os": "linux"
            },
            {
                "name": "OpenJDK8-OPENJ9_ppc64_AIX_jdk8u181-b13_openj9-0.9.0.tar.gz",
                "os": "aix"
            },
            {
                "name": "OpenJDK8-OPENJ9_s390x_Linux_jdk8u181-b13_openj9-0.9.0.tar.gz",
                "os": "linux"
            },
            {
                "name": "OpenJDK8-OPENJ9_x32_Windows_jdk8u181-b13_openj9-0.9.0.zip",
                "os": "windows"
            },
            {
                "name": "OpenJDK8-OPENJ9_x64_LinuxLH_jdk8u181-b13_openj9-0.9.0.tar.gz",
                "os": "linux"
            },
            {
                "name": "OpenJDK8-OPENJ9_x64_Linux_jdk8u181-b13_openj9-0.9.0.tar.gz",
                "os": "linux"
            },
            {
                "name": "OpenJDK8-OPENJ9_x64_Windows_jdk8u181-b13_openj9-0.9.0.zip",
                "os": "windows"
            }
        ]
    },
    {
        "name": "jdk8u191-b12",
        "binaries": [
            {
                "name": "OpenJDK8U-jdk_aarch64_linux_hotspot_8u191b12.tar.gz",
                "os": "linux"
            },
            {
                "name": "OpenJDK8U-jre_aarch64_linux_hotspot_8u191b12.tar.gz",
                "os": "linux"
            }
        ]
    },
    {
        "name": "jdk8u192-b12",
        "binaries": [
            {
                "name": "OpenJDK8U-jdk_ppc64_aix_openj9_8u192b12.tar.gz",
                "os": "aix"
            },
            {
                "name": "OpenJDK8U-jdk_ppc64le_linux_openj9_8u192b12.tar.gz",
                "os": "linux"
            },
            {
                "name": "OpenJDK8U-jdk_s390x_linux_openj9_8u192b12.tar.gz",
                "os": "linux"
            },
            {
                "name": "OpenJDK8U-jdk_x64_linux_openj9_8u192b12.tar.gz",
                "os": "linux"
            },
            {
                "name": "OpenJDK8U-jdk_x64_linux_openj9_linuxXL_8u192b12.tar.gz",
                "os": "linux"
            },
            {
                "name": "OpenJDK8U-jdk_x64_windows_openj9_8u192b12.zip",
                "os": "windows"
            },
            {
                "name": "OpenJDK8U-jdk_x86-32_windows_openj9_8u192b12.zip",
                "os": "windows"
            },
            {
                "name": "OpenJDK8U-jre_ppc64_aix_openj9_8u192b12.tar.gz",
                "os": "aix"
            },
            {
                "name": "OpenJDK8U-jre_ppc64le_linux_openj9_8u192b12.tar.gz",
                "os": "linux"
            },
            {
                "name": "OpenJDK8U-jre_s390x_linux_openj9_8u192b12.tar.gz",
                "os": "linux"
            },
            {
                "name": "OpenJDK8U-jre_x64_linux_openj9_8u192b12.tar.gz",
                "os": "linux"
            },
            {
                "name": "OpenJDK8U-jre_x64_linux_openj9_linuxXL_8u192b12.tar.gz",
                "os": "linux"
            },
            {
                "name": "OpenJDK8U-jre_x64_windows_openj9_8u192b12.zip",
                "os": "windows"
            },
            {
                "name": "OpenJDK8U-jre_x86-32_windows_openj9_8u192b12.zip",
                "os": "windows"
            },
            {
                "name": "OpenJDK8U-jdk_ppc64_aix_hotspot_8u192b12.tar.gz",
                "os": "aix"
            },
            {
                "name": "OpenJDK8U-jdk_s390x_linux_hotspot_8u192b12.tar.gz",
                "os": "linux"
            },
            {
                "name": "OpenJDK8U-jdk_x64_linux_hotspot_8u192b12.tar.gz",
                "os": "linux"
            },
            {
                "name": "OpenJDK8U-jdk_x64_mac_hotspot_8u192b12.tar.gz",
                "os": "mac"
            },
            {
                "name": "OpenJDK8U-jdk_x86-32_windows_hotspot_8u192b12.zip",
                "os": "windows"
            },
            {
                "name": "OpenJDK8U-jre_ppc64_aix_hotspot_8u192b12.tar.gz",
                "os": "aix"
            },
            {
                "name": "OpenJDK8U-jre_s390x_linux_hotspot_8u192b12.tar.gz",
                "os": "linux"
            },
            {
                "name": "OpenJDK8U-jre_x64_linux_hotspot_8u192b12.tar.gz",
                "os": "linux"
            },
            {
                "name": "OpenJDK8U-jre_x64_mac_hotspot_8u192b12.tar.gz",
                "os": "mac"
            },
            {
                "name": "OpenJDK8U-jre_x86-32_windows_hotspot_8u192b12.zip",
                "os": "windows"
            },
            {
                "name": "OpenJDK8U-jdk_ppc64le_linux_hotspot_8u192b12.tar.gz",
                "os": "linux"
            },
            {
                "name": "OpenJDK8U-jre_ppc64le_linux_hotspot_8u192b12.tar.gz",
                "os": "linux"
            },
            {
                "name": "OpenJDK8U-jdk_x64_windows_hotspot_8u192b12.zip",
                "os": "windows"
            },
            {
                "name": "OpenJDK8U-jre_x64_windows_hotspot_8u192b12.zip",
                "os": "windows"
            }
        ]
    },
    {
        "name": "jdk8u192-b12_openj9-0.11.0",
        "binaries": [
            {
                "name": "OpenJDK8U-jre_ppc64le_linux_openj9_8u192b12_openj9-0.11.0.tar.gz",
                "os": "linux"
            },
            {
                "name": "OpenJDK8U-jre_x64_linux_openj9_linuxXL_8u192b12_openj9-0.11.0.tar.gz",
                "os": "linux"
            },
            {
                "name": "OpenJDK8U-jdk_ppc64_aix_openj9_8u192b12_openj9-0.11.0.tar.gz",
                "os": "aix"
            },
            {
                "name": "OpenJDK8U-jdk_ppc64le_linux_openj9_8u192b12_openj9-0.11.0.tar.gz",
                "os": "linux"
            },
            {
                "name": "OpenJDK8U-jdk_s390x_linux_openj9_8u192b12_openj9-0.11.0.tar.gz",
                "os": "linux"
            },
            {
                "name": "OpenJDK8U-jdk_x64_linux_openj9_8u192b12_openj9-0.11.0.tar.gz",
                "os": "linux"
            },
            {
                "name": "OpenJDK8U-jdk_x64_linux_openj9_linuxXL_8u192b12_openj9-0.11.0.tar.gz",
                "os": "linux"
            },
            {
                "name": "OpenJDK8U-jre_ppc64_aix_openj9_8u192b12_openj9-0.11.0.tar.gz",
                "os": "aix"
            },
            {
                "name": "OpenJDK8U-jre_x64_windows_openj9_8u192b12_openj9-0.11.0.zip",
                "os": "windows"
            },
            {
                "name": "OpenJDK8U-jre_x86-32_windows_openj9_8u192b12_openj9-0.11.0.zip",
                "os": "windows"
            },
            {
                "name": "OpenJDK8U-jdk_x86-32_windows_openj9_8u192b12_openj9-0.11.0.zip",
                "os": "windows"
            },
            {
                "name": "OpenJDK8U-jdk_x64_windows_openj9_8u192b12_openj9-0.11.0.zip",
                "os": "windows"
            }
        ]
    },
    {
        "name": "jdk8u202-b08",
        "binaries": [
            {
                "name": "OpenJDK8U-jdk_x64_windows_hotspot_8u202b08.zip",
                "os": "windows"
            },
            {
                "name": "OpenJDK8U-jdk_x86-32_windows_hotspot_8u202b08.zip",
                "os": "windows"
            },
            {
                "name": "OpenJDK8U-jre_x64_windows_hotspot_8u202b08.zip",
                "os": "windows"
            },
            {
                "name": "OpenJDK8U-jre_x86-32_windows_hotspot_8u202b08.zip",
                "os": "windows"
            },
            {
                "name": "OpenJDK8U-jdk_ppc64_aix_hotspot_8u202b08.tar.gz",
                "os": "aix"
            },
            {
                "name": "OpenJDK8U-jdk_ppc64le_linux_hotspot_8u202b08.tar.gz",
                "os": "linux"
            },
            {
                "name": "OpenJDK8U-jdk_s390x_linux_hotspot_8u202b08.tar.gz",
                "os": "linux"
            },
            {
                "name": "OpenJDK8U-jdk_sparcv9_solaris_hotspot_8u202b08.tar.gz",
                "os": "solaris"
            },
            {
                "name": "OpenJDK8U-jre_ppc64_aix_hotspot_8u202b08.tar.gz",
                "os": "aix"
            },
            {
                "name": "OpenJDK8U-jre_ppc64le_linux_hotspot_8u202b08.tar.gz",
                "os": "linux"
            },
            {
                "name": "OpenJDK8U-jre_s390x_linux_hotspot_8u202b08.tar.gz",
                "os": "linux"
            },
            {
                "name": "OpenJDK8U-jre_sparcv9_solaris_hotspot_8u202b08.tar.gz",
                "os": "solaris"
            },
            {
                "name": "OpenJDK8U-jdk_x64_linux_hotspot_8u202b08.tar.gz",
                "os": "linux"
            },
            {
                "name": "OpenJDK8U-jdk_x64_mac_hotspot_8u202b08.tar.gz",
                "os": "mac"
            },
            {
                "name": "OpenJDK8U-jre_x64_linux_hotspot_8u202b08.tar.gz",
                "os": "linux"
            },
            {
                "name": "OpenJDK8U-jre_x64_mac_hotspot_8u202b08.tar.gz",
                "os": "mac"
            },
            {
                "name": "OpenJDK8U-jdk_ppc64_aix_openj9_8u202b08_openj9-0.12.0.tar.gz",
                "os": "aix"
            },
            {
                "name": "OpenJDK8U-jdk_ppc64le_linux_openj9_8u202b08_openj9-0.12.0.tar.gz",
                "os": "linux"
            },
            {
                "name": "OpenJDK8U-jdk_s390x_linux_openj9_8u202b08_openj9-0.12.0.tar.gz",
                "os": "linux"
            },
            {
                "name": "OpenJDK8U-jdk_x64_linux_openj9_linuxXL_8u202b08-openj9-0.12.0.tar.gz",
                "os": "linux"
            },
            {
                "name": "OpenJDK8U-jdk_x64_linux_openj9_8u202b08_openj9-0.12.0.tar.gz",
                "os": "linux"
            },
            {
                "name": "OpenJDK8U-jdk_x64_mac_openj9_8u202b08_openj9-0.12.0.tar.gz",
                "os": "mac"
            },
            {
                "name": "OpenJDK8U-jdk_x64_windows_openj9_8u202b08_openj9-0.12.0.zip",
                "os": "windows"
            },
            {
                "name": "OpenJDK8U-jdk_x86-32_windows_openj9_8u202b08_openj9-0.12.0.zip",
                "os": "windows"
            },
            {
                "name": "OpenJDK8U-jre_ppc64_aix_openj9_8u202b08_openj9-0.12.0.tar.gz",
                "os": "aix"
            },
            {
                "name": "OpenJDK8U-jre_ppc64le_linux_openj9_8u202b08_openj9-0.12.0.tar.gz",
                "os": "linux"
            },
            {
                "name": "OpenJDK8U-jre_s390x_linux_openj9_8u202b08_openj9-0.12.0.tar.gz",
                "os": "linux"
            },
            {
                "name": "OpenJDK8U-jre_x64_linux_openj9_linuxXL_8u202b08-openj9-0.12.0.tar.gz",
                "os": "linux"
            },
            {
                "name": "OpenJDK8U-jre_x64_linux_openj9_8u202b08_openj9-0.12.0.tar.gz",
                "os": "linux"
            },
            {
                "name": "OpenJDK8U-jre_x64_mac_openj9_8u202b08_openj9-0.12.0.tar.gz",
                "os": "mac"
            },
            {
                "name": "OpenJDK8U-jre_x64_windows_openj9_8u202b08_openj9-0.12.0.zip",
                "os": "windows"
            },
            {
                "name": "OpenJDK8U-jre_x86-32_windows_openj9_8u202b08_openj9-0.12.0.zip",
                "os": "windows"
            }
        ]
    },
    {
        "name": "jdk8u202-b08_openj9-0.12.1",
        "binaries": [
            {
                "name": "OpenJDK8U-jdk_ppc64le_linux_openj9_8u202b08_openj9-0.12.1.tar.gz",
                "os": "linux"
            },
            {
                "name": "OpenJDK8U-jdk_s390x_linux_openj9_8u202b08_openj9-0.12.1.tar.gz",
                "os": "linux"
            },
            {
                "name": "OpenJDK8U-jdk_x64_linux_openj9_linuxXL_8u202b08-openj9-0.12.1.tar.gz",
                "os": "linux"
            },
            {
                "name": "OpenJDK8U-jdk_x64_linux_openj9_8u202b08_openj9-0.12.1.tar.gz",
                "os": "linux"
            },
            {
                "name": "OpenJDK8U-jdk_x64_mac_openj9_8u202b08_openj9-0.12.1.tar.gz",
                "os": "mac"
            },
            {
                "name": "OpenJDK8U-jdk_x86-32_windows_openj9_8u202b08_openj9-0.12.1.zip",
                "os": "windows"
            },
            {
                "name": "OpenJDK8U-jre_ppc64le_linux_openj9_8u202b08_openj9-0.12.1.tar.gz",
                "os": "linux"
            },
            {
                "name": "OpenJDK8U-jre_s390x_linux_openj9_8u202b08_openj9-0.12.1.tar.gz",
                "os": "linux"
            },
            {
                "name": "OpenJDK8U-jre_x64_linux_openj9_linuxXL_8u202b08-openj9-0.12.1.tar.gz",
                "os": "linux"
            },
            {
                "name": "OpenJDK8U-jre_x64_linux_openj9_8u202b08_openj9-0.12.1.tar.gz",
                "os": "linux"
            },
            {
                "name": "OpenJDK8U-jre_x64_mac_openj9_8u202b08_openj9-0.12.1.tar.gz",
                "os": "mac"
            },
            {
                "name": "OpenJDK8U-jre_x86-32_windows_openj9_8u202b08_openj9-0.12.1.zip",
                "os": "windows"
            },
            {
                "name": "OpenJDK8U-jdk_ppc64_aix_openj9_8u202b08_openj9-0.12.1.tar.gz",
                "os": "aix"
            },
            {
                "name": "OpenJDK8U-jdk_x64_mac_openj9_macosXL_8u202b08-openj9-0.12.1.tar.gz",
                "os": "mac"
            },
            {
                "name": "OpenJDK8U-jdk_x64_windows_openj9_8u202b08_openj9-0.12.1.zip",
                "os": "windows"
            },
            {
                "name": "OpenJDK8U-jre_ppc64_aix_openj9_8u202b08_openj9-0.12.1.tar.gz",
                "os": "aix"
            },
            {
                "name": "OpenJDK8U-jre_x64_mac_openj9_macosXL_8u202b08-openj9-0.12.1.tar.gz",
                "os": "mac"
            },
            {
                "name": "OpenJDK8U-jre_x64_windows_openj9_8u202b08_openj9-0.12.1.zip",
                "os": "windows"
            },
            {
                "name": "OpenJDK8U-jre_x64_linux_openj9_linuxXL_8u202b08-openj9-0.12.1a.tar.gz",
                "os": "linux"
            },
            {
                "name": "OpenJDK8U-jdk_x64_linux_openj9_linuxXL_8u202b08-openj9-0.12.1a.tar.gz",
                "os": "linux"
            }
        ]
    }
]
